timethis.py
timethis-0.1.2.dist-info/LICENSE
timethis-0.1.2.dist-info/METADATA
timethis-0.1.2.dist-info/WHEEL
timethis-0.1.2.dist-info/top_level.txt
timethis-0.1.2.dist-info/RECORD
