Metadata-Version: 2.1
Name: timethis
Version: 0.1.2
Summary: Context manager for measuring execution times
Home-page: https://github.com/meribold/timethis
Author: Lukas Waymann
Author-email: meribold@gmail.com
Classifier: Development Status :: 4 - Beta
Classifier: Intended Audience :: Developers
Classifier: License :: OSI Approved :: MIT License
Classifier: Operating System :: OS Independent
Classifier: Programming Language :: Python :: 3
Requires-Python: ~=3.6
License-File: LICENSE
